dosk/__init__.py
dosk/dosk.py
tests/__init__.py
tests/min_max_test.py
dosk-0.5.0.dist-info/METADATA
dosk-0.5.0.dist-info/WHEEL
dosk-0.5.0.dist-info/entry_points.txt
dosk-0.5.0.dist-info/top_level.txt
dosk-0.5.0.dist-info/RECORD
